sqlalchemy_authorize/__init__.py
sqlalchemy_authorize/constants.py
sqlalchemy_authorize/permissions_mixin.py
sqlalchemy_authorize/utils.py
sqlalchemy_authorize/oso/__init__.py
sqlalchemy_authorize/oso/oso_permissions_mixin.py
sqlalchemy_authorize-0.1.0.dist-info/AUTHORS.rst
sqlalchemy_authorize-0.1.0.dist-info/LICENSE
sqlalchemy_authorize-0.1.0.dist-info/METADATA
sqlalchemy_authorize-0.1.0.dist-info/WHEEL
sqlalchemy_authorize-0.1.0.dist-info/entry_points.txt
sqlalchemy_authorize-0.1.0.dist-info/top_level.txt
sqlalchemy_authorize-0.1.0.dist-info/RECORD
