Metadata-Version: 2.1
Name: sqlalchemy-authorize
Version: 0.1.0
Summary: An unopinionated extension to enforce role-/relation-/attribute-based access control.
Home-page: https://github.com/jqhoogland/sqlalchemy_authorize
Author: Jesse Hoogland
Author-email: jesse@jessehoogland.com
License: MIT license
Keywords: sqlalchemy_authorize
Platform: UNKNOWN
Classifier: Development Status :: 2 - Pre-Alpha
Classifier: Intended Audience :: Developers
Classifier: License :: OSI Approved :: MIT License
Classifier: Natural Language :: English
Classifier: Programming Language :: Python :: 3
Classifier: Programming Language :: Python :: 3.6
Classifier: Programming Language :: Python :: 3.7
Classifier: Programming Language :: Python :: 3.8
Requires-Python: >=3.6
License-File: LICENSE
License-File: AUTHORS.rst
